gh_auto_updater/__init__.py
gh_auto_updater-0.1.32.dist-info/METADATA
gh_auto_updater-0.1.32.dist-info/WHEEL
gh_auto_updater-0.1.32.dist-info/licenses/LICENSE
gh_auto_updater-0.1.32.dist-info/RECORD
